{"errors":[],"warnings":[],"namedChunkGroups":{"polyfill":{"chunks":[2,8],"assets":["webpack-runtime-056d01bc1f8f8f1795fd.js","webpack-runtime-056d01bc1f8f8f1795fd.js.map","polyfill-57fa76c8ad53bd44c5a1.js","polyfill-57fa76c8ad53bd44c5a1.js.map"],"children":{},"childAssets":{}},"app":{"chunks":[2,7,3],"assets":["webpack-runtime-056d01bc1f8f8f1795fd.js","webpack-runtime-056d01bc1f8f8f1795fd.js.map","framework-dbb498007a7447f28d8e.js","framework-dbb498007a7447f28d8e.js.map","app-6e19204c16e4394fc779.js","app-6e19204c16e4394fc779.js.map"],"children":{},"childAssets":{}},"component---src-pages-404-js":{"chunks":[1,0,4],"assets":["styles.7ec5da06e7c19f79219b.css","styles-e9d24b1846c7d6eb9685.js","styles-e9d24b1846c7d6eb9685.js.map","commons-c006fbbac06e64bb8071.js","commons-c006fbbac06e64bb8071.js.map","component---src-pages-404-js-6763541d3edf3d23ca6c.js","component---src-pages-404-js-6763541d3edf3d23ca6c.js.map"],"children":{},"childAssets":{}},"component---src-pages-index-js":{"chunks":[1,0,5],"assets":["styles.7ec5da06e7c19f79219b.css","styles-e9d24b1846c7d6eb9685.js","styles-e9d24b1846c7d6eb9685.js.map","commons-c006fbbac06e64bb8071.js","commons-c006fbbac06e64bb8071.js.map","component---src-pages-index-js-df5ef67f9aa8bd1207da.js","component---src-pages-index-js-df5ef67f9aa8bd1207da.js.map"],"children":{},"childAssets":{}},"component---src-pages-investments-js":{"chunks":[1,0,6],"assets":["styles.7ec5da06e7c19f79219b.css","styles-e9d24b1846c7d6eb9685.js","styles-e9d24b1846c7d6eb9685.js.map","commons-c006fbbac06e64bb8071.js","commons-c006fbbac06e64bb8071.js.map","component---src-pages-investments-js-82c49b31ba9c8295283d.js","component---src-pages-investments-js-82c49b31ba9c8295283d.js.map"],"children":{},"childAssets":{}}},"assetsByChunkName":{"polyfill":["webpack-runtime-056d01bc1f8f8f1795fd.js","polyfill-57fa76c8ad53bd44c5a1.js"],"app":["webpack-runtime-056d01bc1f8f8f1795fd.js","framework-dbb498007a7447f28d8e.js","app-6e19204c16e4394fc779.js"],"component---src-pages-404-js":["styles.7ec5da06e7c19f79219b.css","styles-e9d24b1846c7d6eb9685.js","commons-c006fbbac06e64bb8071.js","component---src-pages-404-js-6763541d3edf3d23ca6c.js"],"component---src-pages-index-js":["styles.7ec5da06e7c19f79219b.css","styles-e9d24b1846c7d6eb9685.js","commons-c006fbbac06e64bb8071.js","component---src-pages-index-js-df5ef67f9aa8bd1207da.js"],"component---src-pages-investments-js":["styles.7ec5da06e7c19f79219b.css","styles-e9d24b1846c7d6eb9685.js","commons-c006fbbac06e64bb8071.js","component---src-pages-investments-js-82c49b31ba9c8295283d.js"]}}